AUTHORS
ChangeLog
LICENSE
MANIFEST.in
README.rst
requirements.txt
setup.cfg
setup.py
leonardo_counters/__init__.py
leonardo_counters/models.py
leonardo_counters/settings.py
leonardo_counters.egg-info/PKG-INFO
leonardo_counters.egg-info/SOURCES.txt
leonardo_counters.egg-info/dependency_links.txt
leonardo_counters.egg-info/not-zip-safe
leonardo_counters.egg-info/pbr.json
leonardo_counters.egg-info/top_level.txt
leonardo_counters/migrations/__init__.py
leonardo_counters/static/js/lib/jquery.appear.js
leonardo_counters/static/js/lib/jquery.counter.js
leonardo_counters/static/js/lib/jquery.waypoints.min.js
leonardo_counters/templates/widget/countdown/default.html
leonardo_counters/templates/widget/counter/default.html
leonardo_counters/widget/__init__.py
leonardo_counters/widget/countdown/__init__.py
leonardo_counters/widget/countdown/models.py
leonardo_counters/widget/counter/__init__.py
leonardo_counters/widget/counter/models.py
requirements/default.txt